{"namedChunkGroups":{"polyfill":{"name":"polyfill","assets":[{"name":"polyfill.js","size":762955},{"name":"polyfill.2887e79f7dd6d5f62134.hot-update.js","size":866}],"filteredAssets":0,"assetsSize":763821,"filteredAuxiliaryAssets":0,"auxiliaryAssetsSize":0},"commons":{"name":"commons","assets":[{"name":"framework.js","size":2669046},{"name":"commons.css","size":43217},{"name":"commons.js","size":3621992},{"name":"commons.2887e79f7dd6d5f62134.hot-update.js","size":865}],"filteredAssets":0,"assetsSize":6335120,"filteredAuxiliaryAssets":0,"auxiliaryAssetsSize":0},"component---cache-dev-404-page-js":{"name":"component---cache-dev-404-page-js","assets":[{"name":"component---cache-dev-404-page-js.js","size":81056}],"filteredAssets":0,"assetsSize":81056,"filteredAuxiliaryAssets":0,"auxiliaryAssetsSize":0},"component---src-pages-404-jsx":{"name":"component---src-pages-404-jsx","assets":[{"name":"framework.js","size":2669046},{"name":"commons.css","size":43217},{"name":"commons.js","size":3621992},{"name":"commons.2887e79f7dd6d5f62134.hot-update.js","size":865},{"name":"component---src-pages-404-jsx.js","size":388901},{"name":"component---src-pages-404-jsx.2887e79f7dd6d5f62134.hot-update.js","size":14162}],"filteredAssets":0,"assetsSize":6738183,"filteredAuxiliaryAssets":0,"auxiliaryAssetsSize":0},"component---src-pages-cart-jsx":{"name":"component---src-pages-cart-jsx","assets":[{"name":"framework.js","size":2669046},{"name":"commons.css","size":43217},{"name":"commons.js","size":3621992},{"name":"commons.2887e79f7dd6d5f62134.hot-update.js","size":865},{"name":"component---src-pages-cart-jsx.js","size":1569127},{"name":"component---src-pages-cart-jsx.2887e79f7dd6d5f62134.hot-update.js","size":14163}],"filteredAssets":0,"assetsSize":7918410,"filteredAuxiliaryAssets":0,"auxiliaryAssetsSize":0},"component---src-pages-collection-index-js":{"name":"component---src-pages-collection-index-js","assets":[{"name":"framework.js","size":2669046},{"name":"commons.css","size":43217},{"name":"commons.js","size":3621992},{"name":"commons.2887e79f7dd6d5f62134.hot-update.js","size":865},{"name":"component---src-pages-collection-index-js.js","size":465524},{"name":"component---src-pages-collection-index-js.2887e79f7dd6d5f62134.hot-update.js","size":14174}],"filteredAssets":0,"assetsSize":6814818,"filteredAuxiliaryAssets":0,"auxiliaryAssetsSize":0},"component---src-pages-collection-shopify-collection-handle-js":{"name":"component---src-pages-collection-shopify-collection-handle-js","assets":[{"name":"framework.js","size":2669046},{"name":"commons.css","size":43217},{"name":"commons.js","size":3621992},{"name":"commons.2887e79f7dd6d5f62134.hot-update.js","size":865},{"name":"component---src-pages-collection-shopify-collection-handle-js.js","size":457890},{"name":"component---src-pages-collection-shopify-collection-handle-js.2887e79f7dd6d5f62134.hot-update.js","size":14194}],"filteredAssets":0,"assetsSize":6807204,"filteredAuxiliaryAssets":0,"auxiliaryAssetsSize":0},"component---src-pages-index-js":{"name":"component---src-pages-index-js","assets":[{"name":"framework.js","size":2669046},{"name":"commons.css","size":43217},{"name":"commons.js","size":3621992},{"name":"commons.2887e79f7dd6d5f62134.hot-update.js","size":865},{"name":"component---src-pages-index-js.js","size":458626},{"name":"component---src-pages-index-js.2887e79f7dd6d5f62134.hot-update.js","size":14163}],"filteredAssets":0,"assetsSize":6807909,"filteredAuxiliaryAssets":0,"auxiliaryAssetsSize":0},"component---src-pages-product-index-js":{"name":"component---src-pages-product-index-js","assets":[{"name":"framework.js","size":2669046},{"name":"commons.css","size":43217},{"name":"commons.js","size":3621992},{"name":"commons.2887e79f7dd6d5f62134.hot-update.js","size":865},{"name":"component---src-pages-product-index-js.js","size":466305},{"name":"component---src-pages-product-index-js.2887e79f7dd6d5f62134.hot-update.js","size":14171}],"filteredAssets":0,"assetsSize":6815596,"filteredAuxiliaryAssets":0,"auxiliaryAssetsSize":0},"component---src-pages-product-shopify-product-product-type-index-js":{"name":"component---src-pages-product-shopify-product-product-type-index-js","assets":[{"name":"framework.js","size":2669046},{"name":"commons.css","size":43217},{"name":"commons.js","size":3621992},{"name":"commons.2887e79f7dd6d5f62134.hot-update.js","size":865},{"name":"component---src-pages-product-shopify-product-product-type-index-js.js","size":466341},{"name":"component---src-pages-product-shopify-product-product-type-index-js.2887e79f7dd6d5f62134.hot-update.js","size":14200}],"filteredAssets":0,"assetsSize":6815661,"filteredAuxiliaryAssets":0,"auxiliaryAssetsSize":0},"component---src-pages-product-shopify-product-product-type-shopify-product-handle-jsx":{"name":"component---src-pages-product-shopify-product-product-type-shopify-product-handle-jsx","assets":[{"name":"framework.js","size":2669046},{"name":"commons.css","size":43217},{"name":"commons.js","size":3621992},{"name":"commons.2887e79f7dd6d5f62134.hot-update.js","size":865},{"name":"component---src-pages-product-shopify-product-product-type-shopify-product-handle-jsx.js","size":2952643},{"name":"component---src-pages-product-shopify-product-product-type-shopify-product-handle-jsx.2887e79f7dd6d5f62134.hot-update.js","size":14218}],"filteredAssets":0,"assetsSize":9301981,"filteredAuxiliaryAssets":0,"auxiliaryAssetsSize":0},"component---src-pages-search-jsx":{"name":"component---src-pages-search-jsx","assets":[{"name":"framework.js","size":2669046},{"name":"commons.css","size":43217},{"name":"commons.js","size":3621992},{"name":"commons.2887e79f7dd6d5f62134.hot-update.js","size":865},{"name":"component---src-pages-search-jsx.js","size":2522928},{"name":"component---src-pages-search-jsx.2887e79f7dd6d5f62134.hot-update.js","size":14165}],"filteredAssets":0,"assetsSize":8872213,"filteredAuxiliaryAssets":0,"auxiliaryAssetsSize":0}},"assetsByChunkName":{"polyfill":["polyfill.js","polyfill.2887e79f7dd6d5f62134.hot-update.js"],"commons":["framework.js","commons.css","commons.js","commons.2887e79f7dd6d5f62134.hot-update.js"],"component---cache-dev-404-page-js":["component---cache-dev-404-page-js.js"],"component---src-pages-404-jsx":["framework.js","commons.css","commons.js","commons.2887e79f7dd6d5f62134.hot-update.js","component---src-pages-404-jsx.js","component---src-pages-404-jsx.2887e79f7dd6d5f62134.hot-update.js"],"component---src-pages-cart-jsx":["framework.js","commons.css","commons.js","commons.2887e79f7dd6d5f62134.hot-update.js","component---src-pages-cart-jsx.js","component---src-pages-cart-jsx.2887e79f7dd6d5f62134.hot-update.js"],"component---src-pages-collection-index-js":["framework.js","commons.css","commons.js","commons.2887e79f7dd6d5f62134.hot-update.js","component---src-pages-collection-index-js.js","component---src-pages-collection-index-js.2887e79f7dd6d5f62134.hot-update.js"],"component---src-pages-collection-shopify-collection-handle-js":["framework.js","commons.css","commons.js","commons.2887e79f7dd6d5f62134.hot-update.js","component---src-pages-collection-shopify-collection-handle-js.js","component---src-pages-collection-shopify-collection-handle-js.2887e79f7dd6d5f62134.hot-update.js"],"component---src-pages-index-js":["framework.js","commons.css","commons.js","commons.2887e79f7dd6d5f62134.hot-update.js","component---src-pages-index-js.js","component---src-pages-index-js.2887e79f7dd6d5f62134.hot-update.js"],"component---src-pages-product-index-js":["framework.js","commons.css","commons.js","commons.2887e79f7dd6d5f62134.hot-update.js","component---src-pages-product-index-js.js","component---src-pages-product-index-js.2887e79f7dd6d5f62134.hot-update.js"],"component---src-pages-product-shopify-product-product-type-index-js":["framework.js","commons.css","commons.js","commons.2887e79f7dd6d5f62134.hot-update.js","component---src-pages-product-shopify-product-product-type-index-js.js","component---src-pages-product-shopify-product-product-type-index-js.2887e79f7dd6d5f62134.hot-update.js"],"component---src-pages-product-shopify-product-product-type-shopify-product-handle-jsx":["framework.js","commons.css","commons.js","commons.2887e79f7dd6d5f62134.hot-update.js","component---src-pages-product-shopify-product-product-type-shopify-product-handle-jsx.js","component---src-pages-product-shopify-product-product-type-shopify-product-handle-jsx.2887e79f7dd6d5f62134.hot-update.js"],"component---src-pages-search-jsx":["framework.js","commons.css","commons.js","commons.2887e79f7dd6d5f62134.hot-update.js","component---src-pages-search-jsx.js","component---src-pages-search-jsx.2887e79f7dd6d5f62134.hot-update.js"]},"childAssetsByChunkName":{}}